{"name": "England and Wales", "code": "K04000001", "type": "Country", "data": {"care": {"value": {"2011": {"Provides no unpaid care": 58467, "Provides 19 or less hours unpaid care a week": 64989, "Provides 20 to 49 hours unpaid care a week": 61336, "Provides 50 or more hours unpaid care a week": 1655}, "2021": {"Provides no unpaid care": 73188, "Provides 19 or less hours unpaid care a week": 95990, "Provides 20 to 49 hours unpaid care a week": 61565, "Provides 50 or more hours unpaid care a week": 2305}, "change": {"Provides no unpaid care": 14721.0, "Provides 19 or less hours unpaid care a week": 31001.0, "Provides 20 to 49 hours unpaid care a week": 229.0, "Provides 50 or more hours unpaid care a week": 650.0}}, "perc": {"2011": {"Provides no unpaid care": 0.31359, "Provides 19 or less hours unpaid care a week": 0.34857, "Provides 20 to 49 hours unpaid care a week": 0.32897, "Provides 50 or more hours unpaid care a week": 0.00888}, "2021": {"Provides no unpaid care": 0.31405, "Provides 19 or less hours unpaid care a week": 0.41189, "Provides 20 to 49 hours unpaid care a week": 0.26417, "Provides 50 or more hours unpaid care a week": 0.00989}, "change": {"Provides no unpaid care": 0.00046, "Provides 19 or less hours unpaid care a week": 0.06332, "Provides 20 to 49 hours unpaid care a week": -0.0648, "Provides 50 or more hours unpaid care a week": 0.00101}}}, "religion": {"value": {"2011": {"No religion": 70399, "Christian": 12446, "Buddhist": 5767, "Hindu": 64112, "Jewish": 78238, "Muslim": 93981, "Sikh": 2726, "Other religion": 36801, "Not answered": 30609}, "2021": {"No religion": 70200, "Christian": 18444, "Buddhist": 7809, "Hindu": 66220, "Jewish": 81043, "Muslim": 88905, "Sikh": 2049, "Other religion": 54606, "Not answered": 35708}, "change": {"No religion": -199.0, "Christian": 5998.0, "Buddhist": 2042.0, "Hindu": 2108.0, "Jewish": 2805.0, "Muslim": -5076.0, "Sikh": -677.0, "Other religion": 17805.0, "Not answered": 5099.0}}, "perc": {"2011": {"No religion": 0.17819, "Christian": 0.0315, "Buddhist": 0.0146, "Hindu": 0.16228, "Jewish": 0.19803, "Muslim": 0.23788, "Sikh": 0.0069, "Other religion": 0.09315, "Not answered": 0.07748}, "2021": {"No religion": 0.16518, "Christian": 0.0434, "Buddhist": 0.01837, "Hindu": 0.15582, "Jewish": 0.1907, "Muslim": 0.2092, "Sikh": 0.00482, "Other religion": 0.12849, "Not answered": 0.08402}, "change": {"No religion": -0.01301, "Christian": 0.0119, "Buddhist": 0.00377, "Hindu": -0.00646, "Jewish": -0.00733, "Muslim": -0.02868, "Sikh": -0.00208, "Other religion": 0.03534, "Not answered": 0.00654}}}, "ethnicity": {"value": {"2011": {"Asian, Asian British or Asian Welsh": 94074, "Black, Black British, Black Welsh, Caribbean or African": 4996, "Mixed or Multiple ethnic groups": 30029, "White": 53287, "Other ethnic group": 26127}, "2021": {"Asian, Asian British or Asian Welsh": 124096, "Black, Black British, Black Welsh, Caribbean or African": 4282, "Mixed or Multiple ethnic groups": 38844, "White": 53211, "Other ethnic group": 22484}, "change": {"Asian, Asian British or Asian Welsh": 30022.0, "Black, Black British, Black Welsh, Caribbean or African": -714.0, "Mixed or Multiple ethnic groups": 8815.0, "White": -76.0, "Other ethnic group": -3643.0}}, "perc": {"2011": {"Asian, Asian British or Asian Welsh": 0.45117, "Black, Black British, Black Welsh, Caribbean or African": 0.02396, "Mixed or Multiple ethnic groups": 0.14402, "White": 0.25556, "Other ethnic group": 0.1253}, "2021": {"Asian, Asian British or Asian Welsh": 0.51086, "Black, Black British, Black Welsh, Caribbean or African": 0.01763, "Mixed or Multiple ethnic groups": 0.15991, "White": 0.21905, "Other ethnic group": 0.09256}, "change": {"Asian, Asian British or Asian Welsh": 0.05969, "Black, Black British, Black Welsh, Caribbean or African": -0.00633, "Mixed or Multiple ethnic groups": 0.01589, "White": -0.03651, "Other ethnic group": -0.03274}}}, "health": {"value": {"2011": {"Very good or good health": 57471, "Fair health": 34859, "Very bad or bad health": 18470}, "2021": {"Very good or good health": 68808, "Fair health": 45225, "Very bad or bad health": 11617}, "change": {"Very good or good health": 11337.0, "Fair health": 10366.0, "Very bad or bad health": -6853.0}}, "perc": {"2011": {"Very good or good health": 0.51869, "Fair health": 0.31461, "Very bad or bad health": 0.1667}, "2021": {"Very good or good health": 0.54762, "Fair health": 0.35993, "Very bad or bad health": 0.09246}, "change": {"Very good or good health": 0.02893, "Fair health": 0.04532, "Very bad or bad health": -0.07424}}}, "economic": {"value": {"2011": {"Economically active (excluding full-time students): In employment": 60915, "Economically active (excluding full-time students): Unemployed": 16842, "Economically active and a full-time student: In employment": 37228, "Economically active and a full-time student: Unemployed": 49244, "Economically inactive (excluding full-time students)": 25720, "Economically inactive and a full-time student": 31855}, "2021": {"Economically active (excluding full-time students): In employment": 81760, "Economically active (excluding full-time students): Unemployed": 22679, "Economically active and a full-time student: In employment": 48622, "Economically active and a full-time student: Unemployed": 50826, "Economically inactive (excluding full-time students)": 24000, "Economically inactive and a full-time student": 31556}, "change": {"Economically active (excluding full-time students): In employment": 20845.0, "Economically active (excluding full-time students): Unemployed": 5837.0, "Economically active and a full-time student: In employment": 11394.0, "Economically active and a full-time student: Unemployed": 1582.0, "Economically inactive (excluding full-time students)": -1720.0, "Economically inactive and a full-time student": -299.0}}, "perc": {"2011": {"Economically active (excluding full-time students): In employment": 0.27463, "Economically active (excluding full-time students): Unemployed": 0.07593, "Economically active and a full-time student: In employment": 0.16784, "Economically active and a full-time student: Unemployed": 0.22202, "Economically inactive (excluding full-time students)": 0.11596, "Economically inactive and a full-time student": 0.14362}, "2021": {"Economically active (excluding full-time students): In employment": 0.31514, "Economically active (excluding full-time students): Unemployed": 0.08741, "Economically active and a full-time student: In employment": 0.18741, "Economically active and a full-time student: Unemployed": 0.1959, "Economically inactive (excluding full-time students)": 0.09251, "Economically inactive and a full-time student": 0.12163}, "change": {"Economically active (excluding full-time students): In employment": 0.04051, "Economically active (excluding full-time students): Unemployed": 0.01148, "Economically active and a full-time student: In employment": 0.01957, "Economically active and a full-time student: Unemployed": -0.02612, "Economically inactive (excluding full-time students)": -0.02345, "Economically inactive and a full-time student": -0.02199}}}, "household": {"value": {"2011": {"One person household: Aged 66 years and over": 14736, "One person household: Other": 84654, "Single family household: All aged 66 years and over": 20309, "Single family household: Married or civil partnership couple: No children": 24075, "Single family household: Married or civil partnership couple: Dependent children": 56479, "Single family household: Married or civil partnership couple: All children non-dependent": 54289, "Single family household: Cohabiting couple family : No children": 40107, "Single family household: Cohabiting couple family : With dependent children": 77070, "Single family household: Cohabiting couple family : All children non-dependent": 67888, "Single family household: Lone parent family : With dependent children": 74179, "Single family household: Lone parent family : All children non-dependent": 60299, "Single family household: Other single family household: Other family composition": 54135, "Multiple-family household: With dependent children": 20311, "Multiple-Family Household : Other, including all full-time students and all aged 66 years and over": 12815}, "2021": {"One person household: Aged 66 years and over": 19740, "One person household: Other": 82605, "Single family household: All aged 66 years and over": 16985, "Single family household: Married or civil partnership couple: No children": 37899, "Single family household: Married or civil partnership couple: Dependent children": 89259, "Single family household: Married or civil partnership couple: All children non-dependent": 47410, "Single family household: Cohabiting couple family : No children": 44786, "Single family household: Cohabiting couple family : With dependent children": 103808, "Single family household: Cohabiting couple family : All children non-dependent": 52915, "Single family household: Lone parent family : With dependent children": 73281, "Single family household: Lone parent family : All children non-dependent": 73565, "Single family household: Other single family household: Other family composition": 86484, "Multiple-family household: With dependent children": 23646, "Multiple-Family Household : Other, including all full-time students and all aged 66 years and over": 13533}, "change": {"One person household: Aged 66 years and over": 5004.0, "One person household: Other": -2049.0, "Single family household: All aged 66 years and over": -3324.0, "Single family household: Married or civil partnership couple: No children": 13824.0, "Single family household: Married or civil partnership couple: Dependent children": 32780.0, "Single family household: Married or civil partnership couple: All children non-dependent": -6879.0, "Single family household: Cohabiting couple family : No children": 4679.0, "Single family household: Cohabiting couple family : With dependent children": 26738.0, "Single family household: Cohabiting couple family : All children non-dependent": -14973.0, "Single family household: Lone parent family : With dependent children": -898.0, "Single family household: Lone parent family : All children non-dependent": 13266.0, "Single family household: Other single family household: Other family composition": 32349.0, "Multiple-family household: With dependent children": 3335.0, "Multiple-Family Household : Other, including all full-time students and all aged 66 years and over": 718.0}}, "perc": {"2011": {"One person household: Aged 66 years and over": 0.02228, "One person household: Other": 0.128, "Single family household: All aged 66 years and over": 0.03071, "Single family household: Married or civil partnership couple: No children": 0.0364, "Single family household: Married or civil partnership couple: Dependent children": 0.0854, "Single family household: Married or civil partnership couple: All children non-dependent": 0.08209, "Single family household: Cohabiting couple family : No children": 0.06064, "Single family household: Cohabiting couple family : With dependent children": 0.11654, "Single family household: Cohabiting couple family : All children non-dependent": 0.10265, "Single family household: Lone parent family : With dependent children": 0.11216, "Single family household: Lone parent family : All children non-dependent": 0.09118, "Single family household: Other single family household: Other family composition": 0.08186, "Multiple-family household: With dependent children": 0.03071, "Multiple-Family Household : Other, including all full-time students and all aged 66 years and over": 0.01938}, "2021": {"One person household: Aged 66 years and over": 0.02577, "One person household: Other": 0.10785, "Single family household: All aged 66 years and over": 0.02218, "Single family household: Married or civil partnership couple: No children": 0.04948, "Single family household: Married or civil partnership couple: Dependent children": 0.11654, "Single family household: Married or civil partnership couple: All children non-dependent": 0.0619, "Single family household: Cohabiting couple family : No children": 0.05847, "Single family household: Cohabiting couple family : With dependent children": 0.13553, "Single family household: Cohabiting couple family : All children non-dependent": 0.06909, "Single family household: Lone parent family : With dependent children": 0.09568, "Single family household: Lone parent family : All children non-dependent": 0.09605, "Single family household: Other single family household: Other family composition": 0.11292, "Multiple-family household: With dependent children": 0.03087, "Multiple-Family Household : Other, including all full-time students and all aged 66 years and over": 0.01767}, "change": {"One person household: Aged 66 years and over": 0.00349, "One person household: Other": -0.02015, "Single family household: All aged 66 years and over": -0.00853, "Single family household: Married or civil partnership couple: No children": 0.01308, "Single family household: Married or civil partnership couple: Dependent children": 0.03114, "Single family household: Married or civil partnership couple: All children non-dependent": -0.02019, "Single family household: Cohabiting couple family : No children": -0.00217, "Single family household: Cohabiting couple family : With dependent children": 0.01899, "Single family household: Cohabiting couple family : All children non-dependent": -0.03356, "Single family household: Lone parent family : With dependent children": -0.01648, "Single family household: Lone parent family : All children non-dependent": 0.00487, "Single family household: Other single family household: Other family composition": 0.03106, "Multiple-family household: With dependent children": 0.00016, "Multiple-Family Household : Other, including all full-time students and all aged 66 years and over": -0.00171}}}, "marital": {"value": {"2011": {"Never married and never registered a civil partnership": 78260, "Married or in a registered civil partnership": 4453, "Separated, but still legally married or still legally in a civil partnership": 8081, "Divorced or civil partnership dissolved": 76767, "Widowed or surviving civil partnership partner": 53255}, "2021": {"Never married and never registered a civil partnership": 99907, "Married or in a registered civil partnership": 6900, "Separated, but still legally married or still legally in a civil partnership": 10284, "Divorced or civil partnership dissolved": 61997, "Widowed or surviving civil partnership partner": 83627}, "change": {"Never married and never registered a civil partnership": 21647.0, "Married or in a registered civil partnership": 2447.0, "Separated, but still legally married or still legally in a civil partnership": 2203.0, "Divorced or civil partnership dissolved": -14770.0, "Widowed or surviving civil partnership partner": 30372.0}}, "perc": {"2011": {"Never married and never registered a civil partnership": 0.35441, "Married or in a registered civil partnership": 0.02017, "Separated, but still legally married or still legally in a civil partnership": 0.0366, "Divorced or civil partnership dissolved": 0.34765, "Widowed or surviving civil partnership partner": 0.24117}, "2021": {"Never married and never registered a civil partnership": 0.38029, "Married or in a registered civil partnership": 0.02626, "Separated, but still legally married or still legally in a civil partnership": 0.03915, "Divorced or civil partnership dissolved": 0.23599, "Widowed or surviving civil partnership partner": 0.31832}, "change": {"Never married and never registered a civil partnership": 0.02588, "Married or in a registered civil partnership": 0.00609, "Separated, but still legally married or still legally in a civil partnership": 0.00255, "Divorced or civil partnership dissolved": -0.11166, "Widowed or surviving civil partnership partner": 0.07715}}}, "hours": {"value": {"2011": {"Part-time: 15 hours or less worked": 47388, "Part-time: 16 to 30 hours worked": 83226, "Full-time: 31 to 48 hours worked": 55875, "Full-time: 49 or more hours worked": 16723}, "2021": {"Part-time: 15 hours or less worked": 67675, "Part-time: 16 to 30 hours worked": 83679, "Full-time: 31 to 48 hours worked": 73796, "Full-time: 49 or more hours worked": 16167}, "change": {"Part-time: 15 hours or less worked": 20287.0, "Part-time: 16 to 30 hours worked": 453.0, "Full-time: 31 to 48 hours worked": 17921.0, "Full-time: 49 or more hours worked": -556.0}}, "perc": {"2011": {"Part-time: 15 hours or less worked": 0.23319, "Part-time: 16 to 30 hours worked": 0.40955, "Full-time: 31 to 48 hours worked": 0.27496, "Full-time: 49 or more hours worked": 0.08229}, "2021": {"Part-time: 15 hours or less worked": 0.28044, "Part-time: 16 to 30 hours worked": 0.34676, "Full-time: 31 to 48 hours worked": 0.30581, "Full-time: 49 or more hours worked": 0.06699}, "change": {"Part-time: 15 hours or less worked": 0.04725, "Part-time: 16 to 30 hours worked": -0.06279, "Full-time: 31 to 48 hours worked": 0.03085, "Full-time: 49 or more hours worked": -0.0153}}}, "tenure": {"value": {"2011": {"Owns outright or with a mortgage or loan": 75142, "Shared ownership": 64492, "Rented from council or Local Authority": 63302, "Other social rented": 20774, "Private rented": 13996, "Lives rent free": 1211}, "2021": {"Owns outright or with a mortgage or loan": 57026, "Shared ownership": 48482, "Rented from council or Local Authority": 93932, "Other social rented": 29026, "Private rented": 15076, "Lives rent free": 932}, "change": {"Owns outright or with a mortgage or loan": -18116.0, "Shared ownership": -16010.0, "Rented from council or Local Authority": 30630.0, "Other social rented": 8252.0, "Private rented": 1080.0, "Lives rent free": -279.0}}, "perc": {"2011": {"Owns outright or with a mortgage or loan": 0.31451, "Shared ownership": 0.26993, "Rented from council or Local Authority": 0.26495, "Other social rented": 0.08695, "Private rented": 0.05858, "Lives rent free": 0.00507}, "2021": {"Owns outright or with a mortgage or loan": 0.23326, "Shared ownership": 0.19831, "Rented from council or Local Authority": 0.38422, "Other social rented": 0.11873, "Private rented": 0.06167, "Lives rent free": 0.00381}, "change": {"Owns outright or with a mortgage or loan": -0.08125, "Shared ownership": -0.07162, "Rented from council or Local Authority": 0.11927, "Other social rented": 0.03178, "Private rented": 0.00309, "Lives rent free": -0.00126}}}, "disability": {"value": {"2011": {"Disabled under the Equality Act": 43939, "Not disabled under the Equality Act": 68118}, "2021": {"Disabled under the Equality Act": 46977, "Not disabled under the Equality Act": 99112}, "change": {"Disabled under the Equality Act": 3038.0, "Not disabled under the Equality Act": 30994.0}}, "perc": {"2011": {"Disabled under the Equality Act": 0.39211, "Not disabled under the Equality Act": 0.60789}, "2021": {"Disabled under the Equality Act": 0.32156, "Not disabled under the Equality Act": 0.67844}, "change": {"Disabled under the Equality Act": -0.07055, "Not disabled under the Equality Act": 0.07055}}}, "national": {"value": {"2011": {"British only identity": 94686, "Welsh only identity": 29180, "Welsh and British only identity": 1822, "English only identity": 89470, "English and British only identity": 37466, "Any other combination of only UK identities": 99613, "Non-UK identity only": 32536, "UK identity and non-UK identity": 35013}, "2021": {"British only identity": 119576, "Welsh only identity": 37988, "Welsh and British only identity": 2682, "English only identity": 77901, "English and British only identity": 51182, "Any other combination of only UK identities": 137686, "Non-UK identity only": 34492, "UK identity and non-UK identity": 35613}, "change": {"British only identity": 24890.0, "Welsh only identity": 8808.0, "Welsh and British only identity": 860.0, "English only identity": -11569.0, "English and British only identity": 13716.0, "Any other combination of only UK identities": 38073.0, "Non-UK identity only": 1956.0, "UK identity and non-UK identity": 600.0}}, "perc": {"2011": {"British only identity": 0.22556, "Welsh only identity": 0.06951, "Welsh and British only identity": 0.00434, "English only identity": 0.21313, "English and British only identity": 0.08925, "Any other combination of only UK identities": 0.23729, "Non-UK identity only": 0.07751, "UK identity and non-UK identity": 0.08341}, "2021": {"British only identity": 0.24054, "Welsh only identity": 0.07642, "Welsh and British only identity": 0.0054, "English only identity": 0.1567, "English and British only identity": 0.10296, "Any other combination of only UK identities": 0.27697, "Non-UK identity only": 0.06938, "UK identity and non-UK identity": 0.07164}, "change": {"British only identity": 0.01498, "Welsh only identity": 0.00691, "Welsh and British only identity": 0.00106, "English only identity": -0.05643, "English and British only identity": 0.01371, "Any other combination of only UK identities": 0.03968, "Non-UK identity only": -0.00813, "UK identity and non-UK identity": -0.01177}}}, "welsh": {"value": {"2011": {"Can speak Welsh": 75482, "Cannot speak Welsh": 5435}, "2021": {"Can speak Welsh": 85094, "Cannot speak Welsh": 5445}, "change": {"Can speak Welsh": 9612.0, "Cannot speak Welsh": 10.0}}, "perc": {"2011": {"Can speak Welsh": 0.93283, "Cannot speak Welsh": 0.06717}, "2021": {"Can speak Welsh": 0.93986, "Cannot speak Welsh": 0.06014}, "change": {"Can speak Welsh": 0.00703, "Cannot speak Welsh": -0.00703}}}, "population": {"value": {"2011": {"Population": 29748}, "2021": {"Population": 22890}, "change": {"Population": -6858.0}}, "perc": {"2011": {"Population": 1.0}, "2021": {"Population": 1.0}, "change": {"Population": 0.0}}}, "density": {"value": {"2011": {"Density": 60807}, "2021": {"Density": 57103}, "change": {"Density": -3704.0}}, "perc": {"2011": {"Density": 1.0}, "2021": {"Density": 1.0}, "change": {"Density": 0.0}}}, "age10yr": {"value": {"2011": {"0-9": 45334, "10-19": 53139, "20-29": 99178, "30-39": 50309, "40-49": 10862, "50-59": 27016, "60-69": 15014, "70-79": 90007, "80plus": 16191}, "2021": {"0-9": 38906, "10-19": 63929, "20-29": 60411, "30-39": 40077, "40-49": 14586, "50-59": 39118, "60-69": 9069, "70-79": 136955, "80plus": 16574}, "change": {"0-9": -6428.0, "10-19": 10790.0, "20-29": -38767.0, "30-39": -10232.0, "40-49": 3724.0, "50-59": 12102.0, "60-69": -5945.0, "70-79": 46948.0, "80plus": 383.0}}, "perc": {"2011": {"0-9": 0.11137, "10-19": 0.13055, "20-29": 0.24365, "30-39": 0.12359, "40-49": 0.02668, "50-59": 0.06637, "60-69": 0.03688, "70-79": 0.22112, "80plus": 0.03978}, "2021": {"0-9": 0.09272, "10-19": 0.15235, "20-29": 0.14396, "30-39": 0.09551, "40-49": 0.03476, "50-59": 0.09322, "60-69": 0.02161, "70-79": 0.32637, "80plus": 0.0395}, "change": {"0-9": -0.01865, "10-19": 0.0218, "20-29": -0.09969, "30-39": -0.02808, "40-49": 0.00808, "50-59": 0.02685, "60-69": -0.01527, "70-79": 0.10525, "80plus": -0.00028}}}, "agemed": {"value": {"2011": {"Median Age": 44974}, "2021": {"Median Age": 60836}, "change": {"Median Age": 15862.0}}, "perc": {"2011": {"Median Age": 1.0}, "2021": {"Median Age": 1.0}, "change": {"Median Age": 0.0}}}, "cob": {"value": {"2011": {"Elsewhere": 75362, "Afghanistan": 29052, "Albania": 47534, "Antarctica": 57144, "Algeria": 56194, "American Samoa": 73811, "Andorra": 9828, "Angola": 99212, "Antigua and Barbuda": 84573, "Azerbaijan": 91705, "Argentina": 71712, "Australia": 35169, "Austria": 79481, "Bahamas, The": 42498, "Bahrain": 89605, "Bangladesh": 79486, "Armenia": 92828, "Barbados": 84631, "Belgium": 14967, "Bermuda": 80495, "Bhutan": 28417, "Bolivia": 14606, "Bosnia and Herzegovina": 84016, "Botswana": 53249, "Bouvet Island": 70139, "Brazil": 99753, "Belize": 61591, "British Indian Ocean Territory": 8626, "Solomon Islands": 92676, "British Virgin Islands": 4699, "Brunei": 90340, "Bulgaria": 32028, "Myanmar (Burma)": 52738, "Burundi": 18658, "Belarus": 71602, "Cambodia": 53239, "Cameroon": 44329, "Canada": 8554, "Cape Verde": 33756, "Cayman Islands": 97620, "Central African Republic": 88601, "Sri Lanka": 15113, "Chad": 5264, "Chile": 81668, "China": 82546, "Taiwan": 93488, "Christmas Island": 55783, "Cocos (Keeling) Islands": 72486, "Colombia": 33163, "Comoros": 8715, "Mayotte": 45802, "Congo": 22248, "Congo (Democratic Republic)": 849, "Cook Islands": 6600, "Costa Rica": 27490, "Croatia": 90165, "Cuba": 84380, "Czechia": 89286, "Benin": 93966, "Denmark": 50123, "Dominica": 42716, "Dominican Republic": 7586, "Ecuador": 69126, "El Salvador": 56583, "Equatorial Guinea": 41368, "Ethiopia": 38007, "Eritrea": 33064, "Estonia": 28396, "Faroe Islands": 83231, "Falkland Islands": 5565, "South Georgia and the South Sandwich Islands": 83328, "Fiji": 85555, "Finland": 16810, "\u00c5land Islands": 31613, "France": 93024, "French Guiana": 89397, "French Polynesia": 28202, "French Southern Territories": 71467, "Djibouti": 30523, "Gabon": 6599, "Georgia": 11897, "Gambia, The": 32205, "Occupied Palestinian Territories": 74331, "Germany": 81210, "Ghana": 37244, "Gibraltar": 61231, "Kiribati": 73840, "Greece": 59413, "Greenland": 83654, "Grenada": 88615, "Guadeloupe": 75471, "Guam": 40396, "Guatemala": 19128, "Guinea": 15246, "Guyana": 21323, "Haiti": 55642, "Heard Island and McDonald Islands": 58384, "Vatican City": 62828, "Honduras": 8456, "Hong Kong (Special administrative region of China)": 26413, "Hungary": 63367, "Iceland": 27674, "India": 35438, "Indonesia": 10592, "Iran": 55320, "Iraq": 48749, "Ireland": 40937, "Island of Ireland (Not otherwise specified)": 23118, "Israel": 1891, "Italy": 79343, "Ivory Coast": 19624, "Jamaica": 79584, "Japan": 46056, "Kazakhstan": 82387, "Jordan": 45144, "Kenya": 61837, "Korea (North)": 66592, "Korea (South)": 31406, "Kuwait": 52553, "Kyrgyzstan": 89516, "Laos": 84183, "Lebanon": 67391, "Lesotho": 22662, "Latvia": 5575, "Liberia": 82759, "Libya": 58233, "Liechtenstein": 95074, "Lithuania": 48297, "Luxembourg": 35385, "Macao (Special administrative region of China)": 77517, "Madagascar": 21088, "Malawi": 53176, "Malaysia": 13817, "Maldives": 78086, "Mali": 85532, "Malta": 95438, "Martinique": 11371, "Mauritania": 86463, "Mauritius": 64860, "Mexico": 32488, "Monaco": 14576, "Mongolia": 7220, "Moldova": 86480, "Montenegro": 12743, "Montserrat": 99541, "Morocco": 29506, "Mozambique": 59328, "Oman": 45544, "Namibia": 51983, "Nauru": 17373, "Nepal": 88217, "Netherlands": 20189, "Curacao": 76593, "Aruba": 27450, "Sint Maarten (Dutch Part)": 90914, "Bonaire, Sint Eustatius and Saba": 6589, "New Caledonia": 29102, "Vanuatu": 62198, "New Zealand": 59971, "Nicaragua": 54715, "Niger": 87407, "Nigeria": 62877, "Niue": 20998, "Norfolk Island": 15086, "Norway": 21905, "Northern Mariana Islands": 16326, "United States minor outlying islands": 60351, "Micronesia": 13066, "Marshall Islands": 11264, "Palau": 58345, "Pakistan": 17200, "Panama": 3698, "Papua New Guinea": 1499, "Paraguay": 99514, "Peru": 421, "Philippines": 52529, "Pitcairn, Henderson, Ducie and Oeno Islands": 65979, "Poland": 38780, "Portugal": 64133, "Guinea-Bissau": 1102, "East Timor": 36952, "Puerto Rico": 64311, "Qatar": 93024, "R\u00e9union": 24553, "Romania": 74276, "Russia": 23683, "Rwanda": 36802, "St Barth\u00e9lemy": 11615, "St Helena, Ascension and Tristan da Cunha": 37861, "St Kitts and Nevis": 15624, "Anguilla": 70141, "St Lucia": 46596, "St Martin (French part)": 74062, "St Pierre and Miquelon": 88138, "St Vincent and the Grenadines": 59234, "San Marino": 18778, "Sao Tome and Principe": 80476, "Saudi Arabia": 30420, "Senegal": 69917, "Serbia": 87505, "Seychelles": 98349, "Sierra Leone": 28537, "Singapore": 16583, "Slovakia": 3026, "Vietnam": 51649, "Slovenia": 39634, "Somalia": 18266, "South Africa": 16937, "Zimbabwe": 41325, "South Sudan": 46311, "Sudan": 97766, "Western Sahara": 38360, "Suriname": 49364, "Svalbard and Jan Mayen": 66536, "Eswatini": 58918, "Sweden": 54803, "Switzerland": 45509, "Syria": 51369, "Tajikistan": 10504, "Thailand": 71652, "Togo": 59054, "Tokelau": 81796, "Tonga": 26800, "Trinidad and Tobago": 30580, "United Arab Emirates": 91080, "Tunisia": 53724, "Turkey": 31161, "Turkmenistan": 75143, "Turks and Caicos Islands": 80069, "Tuvalu": 53957, "Uganda": 60404, "Ukraine": 13897, "Macedonia": 59493, "Egypt": 69178, "Guernsey": 97709, "Jersey": 363, "Isle of Man": 16478, "Tanzania": 86740, "United States": 85165, "United States Virgin Islands": 82989, "Burkina Faso": 413, "Uruguay": 10995, "Uzbekistan": 54424, "Venezuela": 26930, "Wallis and Futuna": 74974, "Samoa": 84980, "Yemen": 93461, "Zambia": 42795, "Cyprus (European Union)": 27073, "Cyprus (Non-European Union)": 87913, "Cyprus (Not otherwise specified)": 14354, "Spain (Except Canary Islands)": 59853, "Canary Islands": 26807, "Spain (Not otherwise specified)": 98001, "England": 5454, "Northern Ireland": 27010, "Scotland": 21003, "Wales": 19640, "Great Britain (Not otherwise specified)": 74738, "United Kingdom (Not otherwise specified)": 660, "Channel Islands (Not otherwise specified)": 39399, "Kosovo": 30018, "Czechoslovakia (Not otherwise specified)": 31607, "Union of Soviet Socialist Republics (Not otherwise specified)": 46406, "Yugoslavia (Not otherwise specified)": 3977, "Serbia and Montenegro (Not otherwise specified)": 17648, "Europe (Not otherwise specified)": 54769, "Africa (Not otherwise specified)": 90542, "Middle East (Not otherwise specified)": 10411, "Asia (Except Middle East) (Not otherwise specified)": 59051, "North America (Not otherwise specified)": 53604, "Central America (Not otherwise specified)": 62845, "South America (Not otherwise specified)": 19607, "Caribbean (Not otherwise specified)": 79229, "Antarctica and Oceania (Not otherwise specified)": 72560, "At sea": 435, "In the air": 62220, "Netherlands Antilles (Not otherwise specified)": 84641}, "2021": {"Elsewhere": 61031, "Afghanistan": 45480, "Albania": 53581, "Antarctica": 86137, "Algeria": 36689, "American Samoa": 56250, "Andorra": 9040, "Angola": 60769, "Antigua and Barbuda": 91258, "Azerbaijan": 112355, "Argentina": 87004, "Australia": 50355, "Austria": 104918, "Bahamas, The": 29999, "Bahrain": 120882, "Bangladesh": 85310, "Armenia": 62827, "Barbados": 85973, "Belgium": 22986, "Bermuda": 97171, "Bhutan": 45200, "Bolivia": 10188, "Bosnia and Herzegovina": 81962, "Botswana": 64886, "Bouvet Island": 79506, "Brazil": 60546, "Belize": 50489, "British Indian Ocean Territory": 6569, "Solomon Islands": 137696, "British Virgin Islands": 6930, "Brunei": 107327, "Bulgaria": 51017, "Myanmar (Burma)": 34240, "Burundi": 22239, "Belarus": 110912, "Cambodia": 76599, "Cameroon": 64347, "Canada": 13495, "Cape Verde": 28538, "Cayman Islands": 78668, "Central African Republic": 119263, "Sri Lanka": 22591, "Chad": 8105, "Chile": 68486, "China": 86411, "Taiwan": 121725, "Christmas Island": 52756, "Cocos (Keeling) Islands": 75104, "Colombia": 49765, "Comoros": 13333, "Mayotte": 28015, "Congo": 25659, "Congo (Democratic Republic)": 1164, "Cook Islands": 4812, "Costa Rica": 18735, "Croatia": 113276, "Cuba": 68445, "Czechia": 68686, "Benin": 73582, "Denmark": 74392, "Dominica": 65725, "Dominican Republic": 6366, "Ecuador": 72209, "El Salvador": 38931, "Equatorial Guinea": 28697, "Ethiopia": 56979, "Eritrea": 33221, "Estonia": 32296, "Faroe Islands": 130818, "Falkland Islands": 7875, "South Georgia and the South Sandwich Islands": 90647, "Fiji": 55498, "Finland": 24030, "\u00c5land Islands": 35201, "France": 80984, "French Guiana": 56578, "French Polynesia": 40430, "French Southern Territories": 106379, "Djibouti": 45935, "Gabon": 8280, "Georgia": 12853, "Gambia, The": 29528, "Occupied Palestinian Territories": 53003, "Germany": 102623, "Ghana": 32382, "Gibraltar": 95494, "Kiribati": 85002, "Greece": 42755, "Greenland": 120812, "Grenada": 138694, "Guadeloupe": 66432, "Guam": 56035, "Guatemala": 16656, "Guinea": 22389, "Guyana": 27634, "Haiti": 43077, "Heard Island and McDonald Islands": 38620, "Vatican City": 60710, "Honduras": 5559, "Hong Kong (Special administrative region of China)": 27998, "Hungary": 54970, "Iceland": 27491, "India": 51858, "Indonesia": 15224, "Iran": 40146, "Iraq": 40248, "Ireland": 64775, "Island of Ireland (Not otherwise specified)": 24368, "Israel": 2396, "Italy": 122251, "Ivory Coast": 27381, "Jamaica": 68621, "Japan": 68703, "Kazakhstan": 124973, "Jordan": 32852, "Kenya": 83933, "Korea (North)": 77942, "Korea (South)": 36248, "Kuwait": 44316, "Kyrgyzstan": 83822, "Laos": 134620, "Lebanon": 79515, "Lesotho": 20390, "Latvia": 4288, "Liberia": 89620, "Libya": 88450, "Liechtenstein": 140298, "Lithuania": 76302, "Luxembourg": 26381, "Macao (Special administrative region of China)": 113966, "Madagascar": 32815, "Malawi": 59271, "Malaysia": 12078, "Maldives": 92834, "Mali": 133143, "Malta": 94709, "Martinique": 13544, "Mauritania": 81951, "Mauritius": 44295, "Mexico": 30670, "Monaco": 16354, "Mongolia": 5653, "Moldova": 106984, "Montenegro": 16946, "Montserrat": 95581, "Morocco": 23410, "Mozambique": 35981, "Oman": 60351, "Namibia": 67733, "Nauru": 25155, "Nepal": 96676, "Netherlands": 16340, "Curacao": 101119, "Aruba": 22700, "Sint Maarten (Dutch Part)": 140592, "Bonaire, Sint Eustatius and Saba": 5729, "New Caledonia": 29074, "Vanuatu": 45646, "New Zealand": 83519, "Nicaragua": 62720, "Niger": 128008, "Nigeria": 66910, "Niue": 27429, "Norfolk Island": 11946, "Norway": 15897, "Northern Mariana Islands": 14470, "United States minor outlying islands": 67766, "Micronesia": 14639, "Marshall Islands": 13859, "Palau": 53783, "Pakistan": 17506, "Panama": 5687, "Papua New Guinea": 1346, "Paraguay": 118676, "Peru": 417, "Philippines": 55259, "Pitcairn, Henderson, Ducie and Oeno Islands": 75869, "Poland": 32362, "Portugal": 93726, "Guinea-Bissau": 1275, "East Timor": 33871, "Puerto Rico": 72898, "Qatar": 112029, "R\u00e9union": 39038, "Romania": 113060, "Russia": 22486, "Rwanda": 28314, "St Barth\u00e9lemy": 8071, "St Helena, Ascension and Tristan da Cunha": 53739, "St Kitts and Nevis": 18559, "Anguilla": 72293, "St Lucia": 37752, "St Martin (French part)": 100750, "St Pierre and Miquelon": 124415, "St Vincent and the Grenadines": 70054, "San Marino": 14375, "Sao Tome and Principe": 95103, "Saudi Arabia": 20742, "Senegal": 59315, "Serbia": 131389, "Seychelles": 97402, "Sierra Leone": 19011, "Singapore": 26212, "Slovakia": 2998, "Vietnam": 49543, "Slovenia": 36884, "Somalia": 14036, "South Africa": 13483, "Zimbabwe": 39826, "South Sudan": 31515, "Sudan": 61667, "Western Sahara": 60414, "Suriname": 39012, "Svalbard and Jan Mayen": 90010, "Eswatini": 88626, "Sweden": 47293, "Switzerland": 48955, "Syria": 58474, "Tajikistan": 14712, "Thailand": 109946, "Togo": 62146, "Tokelau": 110509, "Tonga": 41597, "Trinidad and Tobago": 20505, "United Arab Emirates": 87828, "Tunisia": 69575, "Turkey": 43379, "Turkmenistan": 114689, "Turks and Caicos Islands": 98445, "Tuvalu": 77046, "Uganda": 89093, "Ukraine": 18502, "Macedonia": 59003, "Egypt": 99507, "Guernsey": 101380, "Jersey": 452, "Isle of Man": 11675, "Tanzania": 103990, "United States": 114002, "United States Virgin Islands": 59817, "Burkina Faso": 434, "Uruguay": 11390, "Uzbekistan": 55201, "Venezuela": 41124, "Wallis and Futuna": 89492, "Samoa": 121775, "Yemen": 100983, "Zambia": 28076, "Cyprus (European Union)": 41542, "Cyprus (Non-European Union)": 109662, "Cyprus (Not otherwise specified)": 22555, "Spain (Except Canary Islands)": 92377, "Canary Islands": 40687, "Spain (Not otherwise specified)": 113514, "England": 3377, "Northern Ireland": 35517, "Scotland": 33056, "Wales": 12371, "Great Britain (Not otherwise specified)": 102600, "United Kingdom (Not otherwise specified)": 910, "Channel Islands (Not otherwise specified)": 62805, "Kosovo": 18712, "Czechoslovakia (Not otherwise specified)": 22029, "Union of Soviet Socialist Republics (Not otherwise specified)": 51141, "Yugoslavia (Not otherwise specified)": 6293, "Serbia and Montenegro (Not otherwise specified)": 14667, "Europe (Not otherwise specified)": 71704, "Africa (Not otherwise specified)": 132271, "Middle East (Not otherwise specified)": 8604, "Asia (Except Middle East) (Not otherwise specified)": 87919, "North America (Not otherwise specified)": 36938, "Central America (Not otherwise specified)": 59150, "South America (Not otherwise specified)": 19716, "Caribbean (Not otherwise specified)": 54791, "Antarctica and Oceania (Not otherwise specified)": 94507, "At sea": 422, "In the air": 72940, "Netherlands Antilles (Not otherwise specified)": 119225}, "change": {"Elsewhere": -14331.0, "Afghanistan": 16428.0, "Albania": 6047.0, "Antarctica": 28993.0, "Algeria": -19505.0, "American Samoa": -17561.0, "Andorra": -788.0, "Angola": -38443.0, "Antigua and Barbuda": 6685.0, "Azerbaijan": 20650.0, "Argentina": 15292.0, "Australia": 15186.0, "Austria": 25437.0, "Bahamas, The": -12499.0, "Bahrain": 31277.0, "Bangladesh": 5824.0, "Armenia": -30001.0, "Barbados": 1342.0, "Belgium": 8019.0, "Bermuda": 16676.0, "Bhutan": 16783.0, "Bolivia": -4418.0, "Bosnia and Herzegovina": -2054.0, "Botswana": 11637.0, "Bouvet Island": 9367.0, "Brazil": -39207.0, "Belize": -11102.0, "British Indian Ocean Territory": -2057.0, "Solomon Islands": 45020.0, "British Virgin Islands": 2231.0, "Brunei": 16987.0, "Bulgaria": 18989.0, "Myanmar (Burma)": -18498.0, "Burundi": 3581.0, "Belarus": 39310.0, "Cambodia": 23360.0, "Cameroon": 20018.0, "Canada": 4941.0, "Cape Verde": -5218.0, "Cayman Islands": -18952.0, "Central African Republic": 30662.0, "Sri Lanka": 7478.0, "Chad": 2841.0, "Chile": -13182.0, "China": 3865.0, "Taiwan": 28237.0, "Christmas Island": -3027.0, "Cocos (Keeling) Islands": 2618.0, "Colombia": 16602.0, "Comoros": 4618.0, "Mayotte": -17787.0, "Congo": 3411.0, "Congo (Democratic Republic)": 315.0, "Cook Islands": -1788.0, "Costa Rica": -8755.0, "Croatia": 23111.0, "Cuba": -15935.0, "Czechia": -20600.0, "Benin": -20384.0, "Denmark": 24269.0, "Dominica": 23009.0, "Dominican Republic": -1220.0, "Ecuador": 3083.0, "El Salvador": -17652.0, "Equatorial Guinea": -12671.0, "Ethiopia": 18972.0, "Eritrea": 157.0, "Estonia": 3900.0, "Faroe Islands": 47587.0, "Falkland Islands": 2310.0, "South Georgia and the South Sandwich Islands": 7319.0, "Fiji": -30057.0, "Finland": 7220.0, "\u00c5land Islands": 3588.0, "France": -12040.0, "French Guiana": -32819.0, "French Polynesia": 12228.0, "French Southern Territories": 34912.0, "Djibouti": 15412.0, "Gabon": 1681.0, "Georgia": 956.0, "Gambia, The": -2677.0, "Occupied Palestinian Territories": -21328.0, "Germany": 21413.0, "Ghana": -4862.0, "Gibraltar": 34263.0, "Kiribati": 11162.0, "Greece": -16658.0, "Greenland": 37158.0, "Grenada": 50079.0, "Guadeloupe": -9039.0, "Guam": 15639.0, "Guatemala": -2472.0, "Guinea": 7143.0, "Guyana": 6311.0, "Haiti": -12565.0, "Heard Island and McDonald Islands": -19764.0, "Vatican City": -2118.0, "Honduras": -2897.0, "Hong Kong (Special administrative region of China)": 1585.0, "Hungary": -8397.0, "Iceland": -183.0, "India": 16420.0, "Indonesia": 4632.0, "Iran": -15174.0, "Iraq": -8501.0, "Ireland": 23838.0, "Island of Ireland (Not otherwise specified)": 1250.0, "Israel": 505.0, "Italy": 42908.0, "Ivory Coast": 7757.0, "Jamaica": -10963.0, "Japan": 22647.0, "Kazakhstan": 42586.0, "Jordan": -12292.0, "Kenya": 22096.0, "Korea (North)": 11350.0, "Korea (South)": 4842.0, "Kuwait": -8237.0, "Kyrgyzstan": -5694.0, "Laos": 50437.0, "Lebanon": 12124.0, "Lesotho": -2272.0, "Latvia": -1287.0, "Liberia": 6861.0, "Libya": 30217.0, "Liechtenstein": 45224.0, "Lithuania": 28005.0, "Luxembourg": -9004.0, "Macao (Special administrative region of China)": 36449.0, "Madagascar": 11727.0, "Malawi": 6095.0, "Malaysia": -1739.0, "Maldives": 14748.0, "Mali": 47611.0, "Malta": -729.0, "Martinique": 2173.0, "Mauritania": -4512.0, "Mauritius": -20565.0, "Mexico": -1818.0, "Monaco": 1778.0, "Mongolia": -1567.0, "Moldova": 20504.0, "Montenegro": 4203.0, "Montserrat": -3960.0, "Morocco": -6096.0, "Mozambique": -23347.0, "Oman": 14807.0, "Namibia": 15750.0, "Nauru": 7782.0, "Nepal": 8459.0, "Netherlands": -3849.0, "Curacao": 24526.0, "Aruba": -4750.0, "Sint Maarten (Dutch Part)": 49678.0, "Bonaire, Sint Eustatius and Saba": -860.0, "New Caledonia": -28.0, "Vanuatu": -16552.0, "New Zealand": 23548.0, "Nicaragua": 8005.0, "Niger": 40601.0, "Nigeria": 4033.0, "Niue": 6431.0, "Norfolk Island": -3140.0, "Norway": -6008.0, "Northern Mariana Islands": -1856.0, "United States minor outlying islands": 7415.0, "Micronesia": 1573.0, "Marshall Islands": 2595.0, "Palau": -4562.0, "Pakistan": 306.0, "Panama": 1989.0, "Papua New Guinea": -153.0, "Paraguay": 19162.0, "Peru": -4.0, "Philippines": 2730.0, "Pitcairn, Henderson, Ducie and Oeno Islands": 9890.0, "Poland": -6418.0, "Portugal": 29593.0, "Guinea-Bissau": 173.0, "East Timor": -3081.0, "Puerto Rico": 8587.0, "Qatar": 19005.0, "R\u00e9union": 14485.0, "Romania": 38784.0, "Russia": -1197.0, "Rwanda": -8488.0, "St Barth\u00e9lemy": -3544.0, "St Helena, Ascension and Tristan da Cunha": 15878.0, "St Kitts and Nevis": 2935.0, "Anguilla": 2152.0, "St Lucia": -8844.0, "St Martin (French part)": 26688.0, "St Pierre and Miquelon": 36277.0, "St Vincent and the Grenadines": 10820.0, "San Marino": -4403.0, "Sao Tome and Principe": 14627.0, "Saudi Arabia": -9678.0, "Senegal": -10602.0, "Serbia": 43884.0, "Seychelles": -947.0, "Sierra Leone": -9526.0, "Singapore": 9629.0, "Slovakia": -28.0, "Vietnam": -2106.0, "Slovenia": -2750.0, "Somalia": -4230.0, "South Africa": -3454.0, "Zimbabwe": -1499.0, "South Sudan": -14796.0, "Sudan": -36099.0, "Western Sahara": 22054.0, "Suriname": -10352.0, "Svalbard and Jan Mayen": 23474.0, "Eswatini": 29708.0, "Sweden": -7510.0, "Switzerland": 3446.0, "Syria": 7105.0, "Tajikistan": 4208.0, "Thailand": 38294.0, "Togo": 3092.0, "Tokelau": 28713.0, "Tonga": 14797.0, "Trinidad and Tobago": -10075.0, "United Arab Emirates": -3252.0, "Tunisia": 15851.0, "Turkey": 12218.0, "Turkmenistan": 39546.0, "Turks and Caicos Islands": 18376.0, "Tuvalu": 23089.0, "Uganda": 28689.0, "Ukraine": 4605.0, "Macedonia": -490.0, "Egypt": 30329.0, "Guernsey": 3671.0, "Jersey": 89.0, "Isle of Man": -4803.0, "Tanzania": 17250.0, "United States": 28837.0, "United States Virgin Islands": -23172.0, "Burkina Faso": 21.0, "Uruguay": 395.0, "Uzbekistan": 777.0, "Venezuela": 14194.0, "Wallis and Futuna": 14518.0, "Samoa": 36795.0, "Yemen": 7522.0, "Zambia": -14719.0, "Cyprus (European Union)": 14469.0, "Cyprus (Non-European Union)": 21749.0, "Cyprus (Not otherwise specified)": 8201.0, "Spain (Except Canary Islands)": 32524.0, "Canary Islands": 13880.0, "Spain (Not otherwise specified)": 15513.0, "England": -2077.0, "Northern Ireland": 8507.0, "Scotland": 12053.0, "Wales": -7269.0, "Great Britain (Not otherwise specified)": 27862.0, "United Kingdom (Not otherwise specified)": 250.0, "Channel Islands (Not otherwise specified)": 23406.0, "Kosovo": -11306.0, "Czechoslovakia (Not otherwise specified)": -9578.0, "Union of Soviet Socialist Republics (Not otherwise specified)": 4735.0, "Yugoslavia (Not otherwise specified)": 2316.0, "Serbia and Montenegro (Not otherwise specified)": -2981.0, "Europe (Not otherwise specified)": 16935.0, "Africa (Not otherwise specified)": 41729.0, "Middle East (Not otherwise specified)": -1807.0, "Asia (Except Middle East) (Not otherwise specified)": 28868.0, "North America (Not otherwise specified)": -16666.0, "Central America (Not otherwise specified)": -3695.0, "South America (Not otherwise specified)": 109.0, "Caribbean (Not otherwise specified)": -24438.0, "Antarctica and Oceania (Not otherwise specified)": 21947.0, "At sea": -13.0, "In the air": 10720.0, "Netherlands Antilles (Not otherwise specified)": 34584.0}}, "perc": {"2011": {"Elsewhere": 0.00546, "Afghanistan": 0.0021, "Albania": 0.00344, "Antarctica": 0.00414, "Algeria": 0.00407, "American Samoa": 0.00535, "Andorra": 0.00071, "Angola": 0.00719, "Antigua and Barbuda": 0.00613, "Azerbaijan": 0.00664, "Argentina": 0.0052, "Australia": 0.00255, "Austria": 0.00576, "Bahamas, The": 0.00308, "Bahrain": 0.00649, "Bangladesh": 0.00576, "Armenia": 0.00673, "Barbados": 0.00613, "Belgium": 0.00108, "Bermuda": 0.00583, "Bhutan": 0.00206, "Bolivia": 0.00106, "Bosnia and Herzegovina": 0.00609, "Botswana": 0.00386, "Bouvet Island": 0.00508, "Brazil": 0.00723, "Belize": 0.00446, "British Indian Ocean Territory": 0.00063, "Solomon Islands": 0.00671, "British Virgin Islands": 0.00034, "Brunei": 0.00655, "Bulgaria": 0.00232, "Myanmar (Burma)": 0.00382, "Burundi": 0.00135, "Belarus": 0.00519, "Cambodia": 0.00386, "Cameroon": 0.00321, "Canada": 0.00062, "Cape Verde": 0.00245, "Cayman Islands": 0.00707, "Central African Republic": 0.00642, "Sri Lanka": 0.0011, "Chad": 0.00038, "Chile": 0.00592, "China": 0.00598, "Taiwan": 0.00677, "Christmas Island": 0.00404, "Cocos (Keeling) Islands": 0.00525, "Colombia": 0.0024, "Comoros": 0.00063, "Mayotte": 0.00332, "Congo": 0.00161, "Congo (Democratic Republic)": 6e-05, "Cook Islands": 0.00048, "Costa Rica": 0.00199, "Croatia": 0.00653, "Cuba": 0.00611, "Czechia": 0.00647, "Benin": 0.00681, "Denmark": 0.00363, "Dominica": 0.0031, "Dominican Republic": 0.00055, "Ecuador": 0.00501, "El Salvador": 0.0041, "Equatorial Guinea": 0.003, "Ethiopia": 0.00275, "Eritrea": 0.0024, "Estonia": 0.00206, "Faroe Islands": 0.00603, "Falkland Islands": 0.0004, "South Georgia and the South Sandwich Islands": 0.00604, "Fiji": 0.0062, "Finland": 0.00122, "\u00c5land Islands": 0.00229, "France": 0.00674, "French Guiana": 0.00648, "French Polynesia": 0.00204, "French Southern Territories": 0.00518, "Djibouti": 0.00221, "Gabon": 0.00048, "Georgia": 0.00086, "Gambia, The": 0.00233, "Occupied Palestinian Territories": 0.00539, "Germany": 0.00588, "Ghana": 0.0027, "Gibraltar": 0.00444, "Kiribati": 0.00535, "Greece": 0.0043, "Greenland": 0.00606, "Grenada": 0.00642, "Guadeloupe": 0.00547, "Guam": 0.00293, "Guatemala": 0.00139, "Guinea": 0.0011, "Guyana": 0.00154, "Haiti": 0.00403, "Heard Island and McDonald Islands": 0.00423, "Vatican City": 0.00455, "Honduras": 0.00061, "Hong Kong (Special administrative region of China)": 0.00191, "Hungary": 0.00459, "Iceland": 0.00201, "India": 0.00257, "Indonesia": 0.00077, "Iran": 0.00401, "Iraq": 0.00353, "Ireland": 0.00297, "Island of Ireland (Not otherwise specified)": 0.00168, "Israel": 0.00014, "Italy": 0.00575, "Ivory Coast": 0.00142, "Jamaica": 0.00577, "Japan": 0.00334, "Kazakhstan": 0.00597, "Jordan": 0.00327, "Kenya": 0.00448, "Korea (North)": 0.00482, "Korea (South)": 0.00228, "Kuwait": 0.00381, "Kyrgyzstan": 0.00649, "Laos": 0.0061, "Lebanon": 0.00488, "Lesotho": 0.00164, "Latvia": 0.0004, "Liberia": 0.006, "Libya": 0.00422, "Liechtenstein": 0.00689, "Lithuania": 0.0035, "Luxembourg": 0.00256, "Macao (Special administrative region of China)": 0.00562, "Madagascar": 0.00153, "Malawi": 0.00385, "Malaysia": 0.001, "Maldives": 0.00566, "Mali": 0.0062, "Malta": 0.00692, "Martinique": 0.00082, "Mauritania": 0.00626, "Mauritius": 0.0047, "Mexico": 0.00235, "Monaco": 0.00106, "Mongolia": 0.00052, "Moldova": 0.00627, "Montenegro": 0.00092, "Montserrat": 0.00721, "Morocco": 0.00214, "Mozambique": 0.0043, "Oman": 0.0033, "Namibia": 0.00377, "Nauru": 0.00126, "Nepal": 0.00639, "Netherlands": 0.00146, "Curacao": 0.00555, "Aruba": 0.00199, "Sint Maarten (Dutch Part)": 0.00659, "Bonaire, Sint Eustatius and Saba": 0.00048, "New Caledonia": 0.00211, "Vanuatu": 0.00451, "New Zealand": 0.00435, "Nicaragua": 0.00396, "Niger": 0.00633, "Nigeria": 0.00456, "Niue": 0.00152, "Norfolk Island": 0.00109, "Norway": 0.00159, "Northern Mariana Islands": 0.00118, "United States minor outlying islands": 0.00437, "Micronesia": 0.00095, "Marshall Islands": 0.00082, "Palau": 0.00423, "Pakistan": 0.00125, "Panama": 0.00027, "Papua New Guinea": 0.00011, "Paraguay": 0.00721, "Peru": 3e-05, "Philippines": 0.00381, "Pitcairn, Henderson, Ducie and Oeno Islands": 0.00478, "Poland": 0.00281, "Portugal": 0.00465, "Guinea-Bissau": 8e-05, "East Timor": 0.00268, "Puerto Rico": 0.00466, "Qatar": 0.00674, "R\u00e9union": 0.00178, "Romania": 0.00538, "Russia": 0.00172, "Rwanda": 0.00267, "St Barth\u00e9lemy": 0.00084, "St Helena, Ascension and Tristan da Cunha": 0.00274, "St Kitts and Nevis": 0.00113, "Anguilla": 0.00508, "St Lucia": 0.00338, "St Martin (French part)": 0.00537, "St Pierre and Miquelon": 0.00639, "St Vincent and the Grenadines": 0.00429, "San Marino": 0.00136, "Sao Tome and Principe": 0.00583, "Saudi Arabia": 0.0022, "Senegal": 0.00507, "Serbia": 0.00634, "Seychelles": 0.00713, "Sierra Leone": 0.00207, "Singapore": 0.0012, "Slovakia": 0.00022, "Vietnam": 0.00374, "Slovenia": 0.00287, "Somalia": 0.00132, "South Africa": 0.00123, "Zimbabwe": 0.00299, "South Sudan": 0.00336, "Sudan": 0.00708, "Western Sahara": 0.00278, "Suriname": 0.00358, "Svalbard and Jan Mayen": 0.00482, "Eswatini": 0.00427, "Sweden": 0.00397, "Switzerland": 0.0033, "Syria": 0.00372, "Tajikistan": 0.00076, "Thailand": 0.00519, "Togo": 0.00428, "Tokelau": 0.00593, "Tonga": 0.00194, "Trinidad and Tobago": 0.00222, "United Arab Emirates": 0.0066, "Tunisia": 0.00389, "Turkey": 0.00226, "Turkmenistan": 0.00544, "Turks and Caicos Islands": 0.0058, "Tuvalu": 0.00391, "Uganda": 0.00438, "Ukraine": 0.00101, "Macedonia": 0.00431, "Egypt": 0.00501, "Guernsey": 0.00708, "Jersey": 3e-05, "Isle of Man": 0.00119, "Tanzania": 0.00628, "United States": 0.00617, "United States Virgin Islands": 0.00601, "Burkina Faso": 3e-05, "Uruguay": 0.0008, "Uzbekistan": 0.00394, "Venezuela": 0.00195, "Wallis and Futuna": 0.00543, "Samoa": 0.00616, "Yemen": 0.00677, "Zambia": 0.0031, "Cyprus (European Union)": 0.00196, "Cyprus (Non-European Union)": 0.00637, "Cyprus (Not otherwise specified)": 0.00104, "Spain (Except Canary Islands)": 0.00434, "Canary Islands": 0.00194, "Spain (Not otherwise specified)": 0.0071, "England": 0.0004, "Northern Ireland": 0.00196, "Scotland": 0.00152, "Wales": 0.00142, "Great Britain (Not otherwise specified)": 0.00542, "United Kingdom (Not otherwise specified)": 5e-05, "Channel Islands (Not otherwise specified)": 0.00285, "Kosovo": 0.00217, "Czechoslovakia (Not otherwise specified)": 0.00229, "Union of Soviet Socialist Republics (Not otherwise specified)": 0.00336, "Yugoslavia (Not otherwise specified)": 0.00029, "Serbia and Montenegro (Not otherwise specified)": 0.00128, "Europe (Not otherwise specified)": 0.00397, "Africa (Not otherwise specified)": 0.00656, "Middle East (Not otherwise specified)": 0.00075, "Asia (Except Middle East) (Not otherwise specified)": 0.00428, "North America (Not otherwise specified)": 0.00388, "Central America (Not otherwise specified)": 0.00455, "South America (Not otherwise specified)": 0.00142, "Caribbean (Not otherwise specified)": 0.00574, "Antarctica and Oceania (Not otherwise specified)": 0.00526, "At sea": 3e-05, "In the air": 0.00451, "Netherlands Antilles (Not otherwise specified)": 0.00613}, "2021": {"Elsewhere": 0.00392, "Afghanistan": 0.00292, "Albania": 0.00344, "Antarctica": 0.00553, "Algeria": 0.00236, "American Samoa": 0.00361, "Andorra": 0.00058, "Angola": 0.0039, "Antigua and Barbuda": 0.00586, "Azerbaijan": 0.00722, "Argentina": 0.00559, "Australia": 0.00323, "Austria": 0.00674, "Bahamas, The": 0.00193, "Bahrain": 0.00776, "Bangladesh": 0.00548, "Armenia": 0.00404, "Barbados": 0.00552, "Belgium": 0.00148, "Bermuda": 0.00624, "Bhutan": 0.0029, "Bolivia": 0.00065, "Bosnia and Herzegovina": 0.00526, "Botswana": 0.00417, "Bouvet Island": 0.00511, "Brazil": 0.00389, "Belize": 0.00324, "British Indian Ocean Territory": 0.00042, "Solomon Islands": 0.00884, "British Virgin Islands": 0.00045, "Brunei": 0.00689, "Bulgaria": 0.00328, "Myanmar (Burma)": 0.0022, "Burundi": 0.00143, "Belarus": 0.00712, "Cambodia": 0.00492, "Cameroon": 0.00413, "Canada": 0.00087, "Cape Verde": 0.00183, "Cayman Islands": 0.00505, "Central African Republic": 0.00766, "Sri Lanka": 0.00145, "Chad": 0.00052, "Chile": 0.0044, "China": 0.00555, "Taiwan": 0.00782, "Christmas Island": 0.00339, "Cocos (Keeling) Islands": 0.00482, "Colombia": 0.0032, "Comoros": 0.00086, "Mayotte": 0.0018, "Congo": 0.00165, "Congo (Democratic Republic)": 7e-05, "Cook Islands": 0.00031, "Costa Rica": 0.0012, "Croatia": 0.00728, "Cuba": 0.0044, "Czechia": 0.00441, "Benin": 0.00473, "Denmark": 0.00478, "Dominica": 0.00422, "Dominican Republic": 0.00041, "Ecuador": 0.00464, "El Salvador": 0.0025, "Equatorial Guinea": 0.00184, "Ethiopia": 0.00366, "Eritrea": 0.00213, "Estonia": 0.00207, "Faroe Islands": 0.0084, "Falkland Islands": 0.00051, "South Georgia and the South Sandwich Islands": 0.00582, "Fiji": 0.00356, "Finland": 0.00154, "\u00c5land Islands": 0.00226, "France": 0.0052, "French Guiana": 0.00363, "French Polynesia": 0.0026, "French Southern Territories": 0.00683, "Djibouti": 0.00295, "Gabon": 0.00053, "Georgia": 0.00083, "Gambia, The": 0.0019, "Occupied Palestinian Territories": 0.0034, "Germany": 0.00659, "Ghana": 0.00208, "Gibraltar": 0.00613, "Kiribati": 0.00546, "Greece": 0.00275, "Greenland": 0.00776, "Grenada": 0.00891, "Guadeloupe": 0.00427, "Guam": 0.0036, "Guatemala": 0.00107, "Guinea": 0.00144, "Guyana": 0.00177, "Haiti": 0.00277, "Heard Island and McDonald Islands": 0.00248, "Vatican City": 0.0039, "Honduras": 0.00036, "Hong Kong (Special administrative region of China)": 0.0018, "Hungary": 0.00353, "Iceland": 0.00177, "India": 0.00333, "Indonesia": 0.00098, "Iran": 0.00258, "Iraq": 0.00259, "Ireland": 0.00416, "Island of Ireland (Not otherwise specified)": 0.00157, "Israel": 0.00015, "Italy": 0.00785, "Ivory Coast": 0.00176, "Jamaica": 0.00441, "Japan": 0.00441, "Kazakhstan": 0.00803, "Jordan": 0.00211, "Kenya": 0.00539, "Korea (North)": 0.00501, "Korea (South)": 0.00233, "Kuwait": 0.00285, "Kyrgyzstan": 0.00538, "Laos": 0.00865, "Lebanon": 0.00511, "Lesotho": 0.00131, "Latvia": 0.00028, "Liberia": 0.00576, "Libya": 0.00568, "Liechtenstein": 0.00901, "Lithuania": 0.0049, "Luxembourg": 0.00169, "Macao (Special administrative region of China)": 0.00732, "Madagascar": 0.00211, "Malawi": 0.00381, "Malaysia": 0.00078, "Maldives": 0.00596, "Mali": 0.00855, "Malta": 0.00608, "Martinique": 0.00087, "Mauritania": 0.00526, "Mauritius": 0.00284, "Mexico": 0.00197, "Monaco": 0.00105, "Mongolia": 0.00036, "Moldova": 0.00687, "Montenegro": 0.00109, "Montserrat": 0.00614, "Morocco": 0.0015, "Mozambique": 0.00231, "Oman": 0.00388, "Namibia": 0.00435, "Nauru": 0.00162, "Nepal": 0.00621, "Netherlands": 0.00105, "Curacao": 0.00649, "Aruba": 0.00146, "Sint Maarten (Dutch Part)": 0.00903, "Bonaire, Sint Eustatius and Saba": 0.00037, "New Caledonia": 0.00187, "Vanuatu": 0.00293, "New Zealand": 0.00536, "Nicaragua": 0.00403, "Niger": 0.00822, "Nigeria": 0.0043, "Niue": 0.00176, "Norfolk Island": 0.00077, "Norway": 0.00102, "Northern Mariana Islands": 0.00093, "United States minor outlying islands": 0.00435, "Micronesia": 0.00094, "Marshall Islands": 0.00089, "Palau": 0.00345, "Pakistan": 0.00112, "Panama": 0.00037, "Papua New Guinea": 9e-05, "Paraguay": 0.00762, "Peru": 3e-05, "Philippines": 0.00355, "Pitcairn, Henderson, Ducie and Oeno Islands": 0.00487, "Poland": 0.00208, "Portugal": 0.00602, "Guinea-Bissau": 8e-05, "East Timor": 0.00218, "Puerto Rico": 0.00468, "Qatar": 0.0072, "R\u00e9union": 0.00251, "Romania": 0.00726, "Russia": 0.00144, "Rwanda": 0.00182, "St Barth\u00e9lemy": 0.00052, "St Helena, Ascension and Tristan da Cunha": 0.00345, "St Kitts and Nevis": 0.00119, "Anguilla": 0.00464, "St Lucia": 0.00242, "St Martin (French part)": 0.00647, "St Pierre and Miquelon": 0.00799, "St Vincent and the Grenadines": 0.0045, "San Marino": 0.00092, "Sao Tome and Principe": 0.00611, "Saudi Arabia": 0.00133, "Senegal": 0.00381, "Serbia": 0.00844, "Seychelles": 0.00626, "Sierra Leone": 0.00122, "Singapore": 0.00168, "Slovakia": 0.00019, "Vietnam": 0.00318, "Slovenia": 0.00237, "Somalia": 0.0009, "South Africa": 0.00087, "Zimbabwe": 0.00256, "South Sudan": 0.00202, "Sudan": 0.00396, "Western Sahara": 0.00388, "Suriname": 0.00251, "Svalbard and Jan Mayen": 0.00578, "Eswatini": 0.00569, "Sweden": 0.00304, "Switzerland": 0.00314, "Syria": 0.00376, "Tajikistan": 0.00094, "Thailand": 0.00706, "Togo": 0.00399, "Tokelau": 0.0071, "Tonga": 0.00267, "Trinidad and Tobago": 0.00132, "United Arab Emirates": 0.00564, "Tunisia": 0.00447, "Turkey": 0.00279, "Turkmenistan": 0.00737, "Turks and Caicos Islands": 0.00632, "Tuvalu": 0.00495, "Uganda": 0.00572, "Ukraine": 0.00119, "Macedonia": 0.00379, "Egypt": 0.00639, "Guernsey": 0.00651, "Jersey": 3e-05, "Isle of Man": 0.00075, "Tanzania": 0.00668, "United States": 0.00732, "United States Virgin Islands": 0.00384, "Burkina Faso": 3e-05, "Uruguay": 0.00073, "Uzbekistan": 0.00355, "Venezuela": 0.00264, "Wallis and Futuna": 0.00575, "Samoa": 0.00782, "Yemen": 0.00649, "Zambia": 0.0018, "Cyprus (European Union)": 0.00267, "Cyprus (Non-European Union)": 0.00704, "Cyprus (Not otherwise specified)": 0.00145, "Spain (Except Canary Islands)": 0.00593, "Canary Islands": 0.00261, "Spain (Not otherwise specified)": 0.00729, "England": 0.00022, "Northern Ireland": 0.00228, "Scotland": 0.00212, "Wales": 0.00079, "Great Britain (Not otherwise specified)": 0.00659, "United Kingdom (Not otherwise specified)": 6e-05, "Channel Islands (Not otherwise specified)": 0.00403, "Kosovo": 0.0012, "Czechoslovakia (Not otherwise specified)": 0.00141, "Union of Soviet Socialist Republics (Not otherwise specified)": 0.00328, "Yugoslavia (Not otherwise specified)": 0.0004, "Serbia and Montenegro (Not otherwise specified)": 0.00094, "Europe (Not otherwise specified)": 0.00461, "Africa (Not otherwise specified)": 0.0085, "Middle East (Not otherwise specified)": 0.00055, "Asia (Except Middle East) (Not otherwise specified)": 0.00565, "North America (Not otherwise specified)": 0.00237, "Central America (Not otherwise specified)": 0.0038, "South America (Not otherwise specified)": 0.00127, "Caribbean (Not otherwise specified)": 0.00352, "Antarctica and Oceania (Not otherwise specified)": 0.00607, "At sea": 3e-05, "In the air": 0.00468, "Netherlands Antilles (Not otherwise specified)": 0.00766}, "change": {"Elsewhere": -0.00154, "Afghanistan": 0.00082, "Albania": 0.0, "Antarctica": 0.00139, "Algeria": -0.00171, "American Samoa": -0.00174, "Andorra": -0.00013, "Angola": -0.00329, "Antigua and Barbuda": -0.00027, "Azerbaijan": 0.00058, "Argentina": 0.00039, "Australia": 0.00068, "Austria": 0.00098, "Bahamas, The": -0.00115, "Bahrain": 0.00127, "Bangladesh": -0.00028, "Armenia": -0.00269, "Barbados": -0.00061, "Belgium": 0.0004, "Bermuda": 0.00041, "Bhutan": 0.00084, "Bolivia": -0.00041, "Bosnia and Herzegovina": -0.00083, "Botswana": 0.00031, "Bouvet Island": 3e-05, "Brazil": -0.00334, "Belize": -0.00122, "British Indian Ocean Territory": -0.00021, "Solomon Islands": 0.00213, "British Virgin Islands": 0.00011, "Brunei": 0.00034, "Bulgaria": 0.00096, "Myanmar (Burma)": -0.00162, "Burundi": 8e-05, "Belarus": 0.00193, "Cambodia": 0.00106, "Cameroon": 0.00092, "Canada": 0.00025, "Cape Verde": -0.00062, "Cayman Islands": -0.00202, "Central African Republic": 0.00124, "Sri Lanka": 0.00035, "Chad": 0.00014, "Chile": -0.00152, "China": -0.00043, "Taiwan": 0.00105, "Christmas Island": -0.00065, "Cocos (Keeling) Islands": -0.00043, "Colombia": 0.0008, "Comoros": 0.00023, "Mayotte": -0.00152, "Congo": 4e-05, "Congo (Democratic Republic)": 1e-05, "Cook Islands": -0.00017, "Costa Rica": -0.00079, "Croatia": 0.00075, "Cuba": -0.00171, "Czechia": -0.00206, "Benin": -0.00208, "Denmark": 0.00115, "Dominica": 0.00112, "Dominican Republic": -0.00014, "Ecuador": -0.00037, "El Salvador": -0.0016, "Equatorial Guinea": -0.00116, "Ethiopia": 0.00091, "Eritrea": -0.00027, "Estonia": 1e-05, "Faroe Islands": 0.00237, "Falkland Islands": 0.00011, "South Georgia and the South Sandwich Islands": -0.00022, "Fiji": -0.00264, "Finland": 0.00032, "\u00c5land Islands": -3e-05, "France": -0.00154, "French Guiana": -0.00285, "French Polynesia": 0.00056, "French Southern Territories": 0.00165, "Djibouti": 0.00074, "Gabon": 5e-05, "Georgia": -3e-05, "Gambia, The": -0.00043, "Occupied Palestinian Territories": -0.00199, "Germany": 0.00071, "Ghana": -0.00062, "Gibraltar": 0.00169, "Kiribati": 0.00011, "Greece": -0.00155, "Greenland": 0.0017, "Grenada": 0.00249, "Guadeloupe": -0.0012, "Guam": 0.00067, "Guatemala": -0.00032, "Guinea": 0.00034, "Guyana": 0.00023, "Haiti": -0.00126, "Heard Island and McDonald Islands": -0.00175, "Vatican City": -0.00065, "Honduras": -0.00025, "Hong Kong (Special administrative region of China)": -0.00011, "Hungary": -0.00106, "Iceland": -0.00024, "India": 0.00076, "Indonesia": 0.00021, "Iran": -0.00143, "Iraq": -0.00094, "Ireland": 0.00119, "Island of Ireland (Not otherwise specified)": -0.00011, "Israel": 1e-05, "Italy": 0.0021, "Ivory Coast": 0.00034, "Jamaica": -0.00136, "Japan": 0.00107, "Kazakhstan": 0.00206, "Jordan": -0.00116, "Kenya": 0.00091, "Korea (North)": 0.00019, "Korea (South)": 5e-05, "Kuwait": -0.00096, "Kyrgyzstan": -0.00111, "Laos": 0.00255, "Lebanon": 0.00023, "Lesotho": -0.00033, "Latvia": -0.00012, "Liberia": -0.00024, "Libya": 0.00146, "Liechtenstein": 0.00212, "Lithuania": 0.0014, "Luxembourg": -0.00087, "Macao (Special administrative region of China)": 0.0017, "Madagascar": 0.00058, "Malawi": -4e-05, "Malaysia": -0.00022, "Maldives": 0.0003, "Mali": 0.00235, "Malta": -0.00084, "Martinique": 5e-05, "Mauritania": -0.001, "Mauritius": -0.00186, "Mexico": -0.00038, "Monaco": -1e-05, "Mongolia": -0.00016, "Moldova": 0.0006, "Montenegro": 0.00017, "Montserrat": -0.00107, "Morocco": -0.00064, "Mozambique": -0.00199, "Oman": 0.00058, "Namibia": 0.00058, "Nauru": 0.00036, "Nepal": -0.00018, "Netherlands": -0.00041, "Curacao": 0.00094, "Aruba": -0.00053, "Sint Maarten (Dutch Part)": 0.00244, "Bonaire, Sint Eustatius and Saba": -0.00011, "New Caledonia": -0.00024, "Vanuatu": -0.00158, "New Zealand": 0.00101, "Nicaragua": 7e-05, "Niger": 0.00189, "Nigeria": -0.00026, "Niue": 0.00024, "Norfolk Island": -0.00032, "Norway": -0.00057, "Northern Mariana Islands": -0.00025, "United States minor outlying islands": -2e-05, "Micronesia": -1e-05, "Marshall Islands": 7e-05, "Palau": -0.00078, "Pakistan": -0.00013, "Panama": 0.0001, "Papua New Guinea": -2e-05, "Paraguay": 0.00041, "Peru": 0.0, "Philippines": -0.00026, "Pitcairn, Henderson, Ducie and Oeno Islands": 9e-05, "Poland": -0.00073, "Portugal": 0.00137, "Guinea-Bissau": 0.0, "East Timor": -0.0005, "Puerto Rico": 2e-05, "Qatar": 0.00046, "R\u00e9union": 0.00073, "Romania": 0.00188, "Russia": -0.00028, "Rwanda": -0.00085, "St Barth\u00e9lemy": -0.00032, "St Helena, Ascension and Tristan da Cunha": 0.00071, "St Kitts and Nevis": 6e-05, "Anguilla": -0.00044, "St Lucia": -0.00096, "St Martin (French part)": 0.0011, "St Pierre and Miquelon": 0.0016, "St Vincent and the Grenadines": 0.00021, "San Marino": -0.00044, "Sao Tome and Principe": 0.00028, "Saudi Arabia": -0.00087, "Senegal": -0.00126, "Serbia": 0.0021, "Seychelles": -0.00087, "Sierra Leone": -0.00085, "Singapore": 0.00048, "Slovakia": -3e-05, "Vietnam": -0.00056, "Slovenia": -0.0005, "Somalia": -0.00042, "South Africa": -0.00036, "Zimbabwe": -0.00043, "South Sudan": -0.00134, "Sudan": -0.00312, "Western Sahara": 0.0011, "Suriname": -0.00107, "Svalbard and Jan Mayen": 0.00096, "Eswatini": 0.00142, "Sweden": -0.00093, "Switzerland": -0.00016, "Syria": 4e-05, "Tajikistan": 0.00018, "Thailand": 0.00187, "Togo": -0.00029, "Tokelau": 0.00117, "Tonga": 0.00073, "Trinidad and Tobago": -0.0009, "United Arab Emirates": -0.00096, "Tunisia": 0.00058, "Turkey": 0.00053, "Turkmenistan": 0.00193, "Turks and Caicos Islands": 0.00052, "Tuvalu": 0.00104, "Uganda": 0.00134, "Ukraine": 0.00018, "Macedonia": -0.00052, "Egypt": 0.00138, "Guernsey": -0.00057, "Jersey": 0.0, "Isle of Man": -0.00044, "Tanzania": 0.0004, "United States": 0.00115, "United States Virgin Islands": -0.00217, "Burkina Faso": 0.0, "Uruguay": -7e-05, "Uzbekistan": -0.00039, "Venezuela": 0.00069, "Wallis and Futuna": 0.00032, "Samoa": 0.00166, "Yemen": -0.00028, "Zambia": -0.0013, "Cyprus (European Union)": 0.00071, "Cyprus (Non-European Union)": 0.00067, "Cyprus (Not otherwise specified)": 0.00041, "Spain (Except Canary Islands)": 0.00159, "Canary Islands": 0.00067, "Spain (Not otherwise specified)": 0.00019, "England": -0.00018, "Northern Ireland": 0.00032, "Scotland": 0.0006, "Wales": -0.00063, "Great Britain (Not otherwise specified)": 0.00117, "United Kingdom (Not otherwise specified)": 1e-05, "Channel Islands (Not otherwise specified)": 0.00118, "Kosovo": -0.00097, "Czechoslovakia (Not otherwise specified)": -0.00088, "Union of Soviet Socialist Republics (Not otherwise specified)": -8e-05, "Yugoslavia (Not otherwise specified)": 0.00011, "Serbia and Montenegro (Not otherwise specified)": -0.00034, "Europe (Not otherwise specified)": 0.00064, "Africa (Not otherwise specified)": 0.00194, "Middle East (Not otherwise specified)": -0.0002, "Asia (Except Middle East) (Not otherwise specified)": 0.00137, "North America (Not otherwise specified)": -0.00151, "Central America (Not otherwise specified)": -0.00075, "South America (Not otherwise specified)": -0.00015, "Caribbean (Not otherwise specified)": -0.00222, "Antarctica and Oceania (Not otherwise specified)": 0.00081, "At sea": 0.0, "In the air": 0.00017, "Netherlands Antilles (Not otherwise specified)": 0.00153}}}}}